{
  "special": {
    "background": "#1b181b",
    "foreground": "#f7f3f7",
    "cursor": "#f7f3f7"
  },
  "colors": {
    "color0": "#1b181b",
    "color1": "#292329",
    "color2": "#695d69",
    "color3": "#776977",
    "color4": "#9e8f9e",
    "color5": "#ab9bab",
    "color6": "#d8cad8",
    "color7": "#f7f3f7",
    "color8": "#ca402b",
    "color9": "#a65926",
    "color10": "#bb8a35",
    "color11": "#918b3b",
    "color12": "#159393",
    "color13": "#516aec",
    "color14": "#7b59c0",
    "color15": "#cc33cc"
  }
}
